pxmap/__init__.py
pxmap-0.0.2.dist-info/LICENSE
pxmap-0.0.2.dist-info/METADATA
pxmap-0.0.2.dist-info/WHEEL
pxmap-0.0.2.dist-info/top_level.txt
pxmap-0.0.2.dist-info/RECORD
