Metadata-Version: 2.1
Name: pxmap
Version: 0.0.2
Summary: Streamlit component for Plotly express
Home-page: UNKNOWN
Author: Jose Manuel Napoles Duarte
Author-email: jnapoles@uach.mx
License: UNKNOWN
Platform: UNKNOWN
Requires-Python: >=3.6
Requires-Dist: streamlit (>=0.63)
Requires-Dist: plotly (>=4.14.3)
